Rabbi/__init__.py
Rabbi/core.py
Rabbi-0.1.0.dist-info/LICENSE
Rabbi-0.1.0.dist-info/METADATA
Rabbi-0.1.0.dist-info/WHEEL
Rabbi-0.1.0.dist-info/top_level.txt
Rabbi-0.1.0.dist-info/RECORD
