Metadata-Version: 2.1
Name: Rabbi
Version: 0.1.0
Summary: A machine learning package for preprocessing and model training.
Home-page: https://github.com/sarthakm402/Automated_ML
Author: Sarthak Mohapatra
Classifier: Programming Language :: Python :: 3
Classifier: License :: OSI Approved :: GNU General Public License v3 (GPLv3)
Classifier: Operating System :: OS Independent
Requires-Python: >=3.7
License-File: LICENSE
Requires-Dist: numpy
Requires-Dist: pandas
Requires-Dist: scikit-learn
Requires-Dist: seaborn
Requires-Dist: xgboost
Requires-Dist: optuna
